{
	"format_version": "1.8.0",
	"animations": {
		"animation.lituly.move": {
			"loop": true,
			"animation_length": 1,
			"bones": {
				"back_left": {
					"rotation": {
						"0.0": {
							"vector": [0, 0, 0]
						},
						"0.25": {
							"vector": [0, -15, 0.00002],
							"easing": "linear"
						},
						"0.5": {
							"vector": [0, 0, 0],
							"easing": "linear"
						},
						"0.75": {
							"vector": [0, 15, -0.00002],
							"easing": "linear"
						},
						"1.0": {
							"vector": [0, 0, 0],
							"easing": "linear"
						}
					}
				},
				"back_right": {
					"rotation": {
						"0.0": {
							"vector": [0, 0, 0]
						},
						"0.25": {
							"vector": [0, 17.5, -0.00002],
							"easing": "linear"
						},
						"0.5": {
							"vector": [0, 0, 0],
							"easing": "linear"
						},
						"0.75": {
							"vector": [0, -15, 0.00002],
							"easing": "linear"
						},
						"1.0": {
							"vector": [0, 0, 0],
							"easing": "linear"
						}
					}
				},
				"middle_left": {
					"rotation": {
						"0.0": {
							"vector": [0, 0, 0]
						},
						"0.25": {
							"vector": [0, 15, -0.00002],
							"easing": "linear"
						},
						"0.5": {
							"vector": [0, 0, 0],
							"easing": "linear"
						},
						"0.75": {
							"vector": [0, -15, 0.00002],
							"easing": "linear"
						},
						"1.0": {
							"vector": [0, 0, 0],
							"easing": "linear"
						}
					}
				},
				"middle_right": {
					"rotation": {
						"0.0": {
							"vector": [0, 0, 0]
						},
						"0.25": {
							"vector": [0, -15, 0.00002],
							"easing": "linear"
						},
						"0.5": {
							"vector": [0, 0, 0],
							"easing": "linear"
						},
						"0.75": {
							"vector": [0, 15, -0.00002],
							"easing": "linear"
						},
						"1.0": {
							"vector": [0, 0, 0],
							"easing": "linear"
						}
					}
				},
				"front_left": {
					"rotation": {
						"0.0": {
							"vector": [0, 0, 0]
						},
						"0.25": {
							"vector": [0, -15, 0.00002],
							"easing": "linear"
						},
						"0.5": {
							"vector": [0, 0, 0],
							"easing": "linear"
						},
						"0.75": {
							"vector": [0, 15, -0.00002],
							"easing": "linear"
						},
						"1.0": {
							"vector": [0, 0, 0],
							"easing": "linear"
						}
					}
				},
				"front_right": {
					"rotation": {
						"0.0": {
							"vector": [0, 0, 0]
						},
						"0.25": {
							"vector": [0, 15, -0.00002],
							"easing": "linear"
						},
						"0.5": {
							"vector": [0, 0, 0],
							"easing": "linear"
						},
						"0.75": {
							"vector": [0, -15, 0.00002],
							"easing": "linear"
						},
						"1.0": {
							"vector": [0, 0, 0],
							"easing": "linear"
						}
					}
				}
			}
		}
	},
	"geckolib_format_version": 2
}